texpr/__init__.py
texpr/__main__.py
texpr/py.typed
texpr/actions/__init__.py
texpr/actions/textpress_convert.py
texpr/actions/textpress_format.py
texpr/actions/textpress_publish.py
texpr/actions/textpress_render_template.py
texpr/api/__init__.py
texpr/api/http_client.py
texpr/api/textpress_api.py
texpr/api/textpress_env.py
texpr/cli/__init__.py
texpr/cli/cli_commands.py
texpr/cli/cli_main.py
texpr/cli/cli_setup.py
texpr/docs/__init__.py
texpr/docs/doc_cleanups.py
texpr/docs/render_webpage.py
texpr/docs/templates/textpress_webpage.html.jinja
texpr-0.0.8.dist-info/METADATA
texpr-0.0.8.dist-info/WHEEL
texpr-0.0.8.dist-info/entry_points.txt
texpr-0.0.8.dist-info/licenses/LICENSE
texpr-0.0.8.dist-info/RECORD
